mailman-3.3.10.dist-info/METADATA
mailman-3.3.10.dist-info/WHEEL
mailman-3.3.10.dist-info/entry_points.txt
mailman-3.3.10.dist-info/licenses/COPYING
mailman/__init__.py
mailman/app/__init__.py
mailman/app/bounces.py
mailman/app/commands.py
mailman/app/digests.py
mailman/app/docs/__init__.py
mailman/app/docs/app.rst
mailman/app/docs/bans.rst
mailman/app/docs/bounces.rst
mailman/app/docs/lifecycle.rst
mailman/app/docs/message.rst
mailman/app/docs/moderator.rst
mailman/app/docs/pipelines.rst
mailman/app/docs/system.rst
mailman/app/domain.py
mailman/app/events.py
mailman/app/inject.py
mailman/app/lifecycle.py
mailman/app/membership.py
mailman/app/moderator.py
mailman/app/notifications.py
mailman/app/replybot.py
mailman/app/subscriptions.py
mailman/app/tests/__init__.py
mailman/app/tests/test_bounces.py
mailman/app/tests/test_digests.py
mailman/app/tests/test_inject.py
mailman/app/tests/test_lifecycle.py
mailman/app/tests/test_membership.py
mailman/app/tests/test_moderation.py
mailman/app/tests/test_notifications.py
mailman/app/tests/test_subscriptions.py
mailman/app/tests/test_unsubscriptions.py
mailman/app/tests/test_workflow.py
mailman/app/tests/test_workflowmanager.py
mailman/app/workflow.py
mailman/archiving/__init__.py
mailman/archiving/docs/__init__.py
mailman/archiving/docs/common.rst
mailman/archiving/mailarchive.py
mailman/archiving/mhonarc.py
mailman/archiving/prototype.py
mailman/archiving/tests/__init__.py
mailman/archiving/tests/fake_mhonarc.py
mailman/archiving/tests/test_mhonarc.py
mailman/archiving/tests/test_prototype.py
mailman/bin/__init__.py
mailman/bin/docs/master.rst
mailman/bin/mailman.py
mailman/bin/master.py
mailman/bin/runner.py
mailman/bin/tests/__init__.py
mailman/bin/tests/test_mailman.py
mailman/bin/tests/test_master.py
mailman/chains/__init__.py
mailman/chains/accept.py
mailman/chains/base.py
mailman/chains/builtin.py
mailman/chains/discard.py
mailman/chains/dmarc.py
mailman/chains/docs/__init__.py
mailman/chains/docs/chains.rst
mailman/chains/docs/moderation.rst
mailman/chains/headers.py
mailman/chains/hold.py
mailman/chains/moderation.py
mailman/chains/owner.py
mailman-3.3.10.dist-info/RECORD
